[
  {
    "Id": 1,
    "ProductId": 1,
    "PicPath": "DEMO喵喵.jpg"
  },
  {
    "Id": 2,
    "ProductId": 2,
    "PicPath": "DEMO鮭魚.jpg"
  },
  {
    "Id": 3,
    "ProductId": 3,
    "PicPath": "DEMO記憶體.jpg"
  },
  {
    "Id": 4,
    "ProductId": 4,
    "PicPath": "DEMO月亮蝦餅.jpg"
  },
  {
    "Id": 5,
    "ProductId": 5,
    "PicPath": "DEMO牛排.jpg"
  },
  {
    "Id": 6,
    "ProductId": 6,
    "PicPath": "DEMO雪糕.jpg"
  },
  {
    "Id": 7,
    "ProductId": 7,
    "PicPath": "DEMO披薩.jpg"
  },
  {
    "Id": 8,
    "ProductId": 5,
    "PicPath": "DEMO牛排1.jpg"
  }
]